{
  "version": 1,
  "mission_slug": "design-system-remediation-and-demo-01KQKSSR",
  "mission_id": "01KQKSSREGP0J8P6WRN2F19F6R",
  "mission_branch": "kitty/mission-design-system-remediation-and-demo-01KQKSSR",
  "target_branch": "main",
  "lanes": [
    {
      "lane_id": "lane-a",
      "wp_ids": [
        "WP01",
        "WP02",
        "WP03",
        "WP04"
      ],
      "write_scope": [
        "apps/demo/blog-demo.html",
        "apps/demo/dashboard-demo.html",
        "apps/demo/index.html",
        "packages/angular/src/lib/button/sk-button-ghost.component.ts",
        "packages/angular/src/lib/button/sk-button-primary.component.ts",
        "packages/angular/src/lib/button/sk-button-secondary.component.ts",
        "packages/angular/src/lib/card/**",
        "packages/html-js/src/button/sk-button-html.stories.ts",
        "packages/html-js/src/card/**",
        "packages/html-js/src/check-bullet/sk-check-bullet-html.stories.ts",
        "packages/html-js/src/feature-card/sk-feature-card-html.stories.ts",
        "packages/html-js/src/form-field/sk-form-field-html.stories.ts",
        "packages/html-js/src/ribbon-card/sk-ribbon-card-html.stories.ts",
        "packages/html-js/src/section-banner/sk-section-banner-html.stories.ts"
      ],
      "predicted_surfaces": [
        "api",
        "app-shell",
        "artifact-rendering",
        "dashboard",
        "workspace"
      ],
      "depends_on_lanes": [],
      "parallel_group": 0
    }
  ],
  "computed_at": "2026-05-02T07:42:49.551065+00:00",
  "computed_from": "dependency_graph+ownership",
  "planning_artifact_wps": [],
  "collapse_report": {
    "events": [
      {
        "wp_a": "WP03",
        "wp_b": "WP02",
        "rule": "dependency",
        "evidence": "WP03 depends on WP02"
      },
      {
        "wp_a": "WP04",
        "wp_b": "WP01",
        "rule": "dependency",
        "evidence": "WP04 depends on WP01"
      },
      {
        "wp_a": "WP04",
        "wp_b": "WP02",
        "rule": "dependency",
        "evidence": "WP04 depends on WP02"
      }
    ],
    "total_merges": 3,
    "independent_wps_collapsed": 0,
    "by_rule": {
      "dependency": 3
    }
  }
}
